<?xml version="1.0" encoding="utf-8"?>
<TextureAtlas imagePath="bf explosion.png">
	<!-- Created with Adobe Animate version 21.0.9.42677 -->
	<!-- http://www.adobe.com/products/animate.html -->
	<SubTexture name="badniks explosion defeat w-0 flickie instance 10000" x="0" y="0" width="855" height="864"/>
	<SubTexture name="badniks explosion defeat w-0 flickie instance 10001" x="855" y="0" width="855" height="864"/>
	<SubTexture name="badniks explosion defeat w-0 flickie instance 10002" x="1710" y="0" width="855" height="864"/>
	<SubTexture name="badniks explosion defeat w-0 flickie instance 10003" x="2565" y="0" width="855" height="864"/>
	<SubTexture name="badniks explosion defeat w-0 flickie instance 10004" x="0" y="864" width="855" height="864"/>
	<SubTexture name="badniks explosion defeat w-0 flickie instance 10005" x="0" y="864" width="855" height="864"/>
	<SubTexture name="badniks explosion defeat w-0 flickie instance 10006" x="855" y="864" width="855" height="864"/>
	<SubTexture name="badniks explosion defeat w-0 flickie instance 10007" x="855" y="864" width="855" height="864"/>
	<SubTexture name="badniks explosion defeat w-0 flickie instance 10008" x="1710" y="864" width="855" height="864"/>
	<SubTexture name="badniks explosion defeat w-0 flickie instance 10009" x="1710" y="864" width="855" height="864"/>
	<SubTexture name="badniks explosion defeat w-0 flickie instance 10010" x="2565" y="864" width="855" height="864"/>
	<SubTexture name="badniks explosion defeat w-0 flickie instance 10011" x="2565" y="864" width="855" height="864"/>
	<SubTexture name="badniks explosion defeat w-0 flickie instance 10012" x="0" y="1728" width="855" height="864"/>
	<SubTexture name="badniks explosion defeat w-0 flickie instance 10013" x="0" y="1728" width="855" height="864"/>
	<SubTexture name="badniks explosion defeat w-0 flickie instance 10014" x="855" y="1728" width="855" height="864"/>
	<SubTexture name="badniks explosion defeat w-0 flickie instance 10015" x="855" y="1728" width="855" height="864"/>
	<SubTexture name="badniks explosion defeat w-0 flickie instance 10016" x="1710" y="1728" width="855" height="864"/>
	<SubTexture name="badniks explosion defeat w-0 flickie instance 10017" x="1710" y="1728" width="855" height="864"/>
	<SubTexture name="badniks explosion defeat w-0 flickie instance 10018" x="2565" y="1728" width="855" height="864"/>
	<SubTexture name="badniks explosion defeat w-0 flickie instance 10019" x="2565" y="1728" width="855" height="864"/>
	<SubTexture name="badniks explosion defeat w-0 flickie instance 10020" x="2565" y="1728" width="855" height="864"/>
	<SubTexture name="badniks explosion defeat w-0 flickie instance 10021" x="0" y="2592" width="855" height="864"/>
	<SubTexture name="badniks explosion defeat w-0 flickie instance 10022" x="0" y="2592" width="855" height="864"/>
	<SubTexture name="badniks explosion defeat w-0 flickie instance 10023" x="0" y="2592" width="855" height="864"/>
	<SubTexture name="badniks explosion defeat w-0 flickie instance 10024" x="855" y="2592" width="855" height="864"/>
	<SubTexture name="badniks explosion defeat w-0 flickie instance 10025" x="855" y="2592" width="855" height="864"/>
	<SubTexture name="badniks explosion defeat w-0 flickie instance 10026" x="855" y="2592" width="855" height="864"/>
</TextureAtlas>
