<?xml version="1.0" encoding="UTF-8"?>
<TextureAtlas imagePath="parappapixel.png">
	<!-- Created with Adobe Flash CS6 version 12.0.0.481 -->
	<!-- http://www.adobe.com/products/flash.html -->
	<SubTexture name="idle0001" x="0" y="0" width="73" height="45" frameX="25" frameY="0" frameWidth="73" frameHeight="45"/>
	
	<SubTexture name="confirm0001" x="0" y="0" width="73" height="45" frameX="25" frameY="0" frameWidth="73" frameHeight="45"/>
	<SubTexture name="confirm0002" x="73" y="0" width="73" height="45" frameX="25" frameY="0" frameWidth="73" frameHeight="45"/>
	<SubTexture name="confirm0003" x="0" y="45" width="73" height="45" frameX="25" frameY="0" frameWidth="73" frameHeight="45"/>
	<SubTexture name="confirm0004" x="73" y="45" width="73" height="45" frameX="25" frameY="0" frameWidth="73" frameHeight="45"/>
	<SubTexture name="confirm0005" x="0" y="45" width="73" height="45" frameX="25" frameY="0" frameWidth="73" frameHeight="45"/>
	<SubTexture name="confirm0006" x="73" y="45" width="73" height="45" frameX="25" frameY="0" frameWidth="73" frameHeight="45"/>
	<SubTexture name="confirm0007" x="0" y="45" width="73" height="45" frameX="25" frameY="0" frameWidth="73" frameHeight="45"/>
	<SubTexture name="confirm0008" x="73" y="45" width="73" height="45" frameX="25" frameY="0" frameWidth="73" frameHeight="45"/>
	
	<SubTexture name="confirm-hold0001" x="73" y="45" width="73" height="45" frameX="25" frameY="0" frameWidth="73" frameHeight="45"/>
</TextureAtlas>
