{
	"animations": [
		{
			"offsets": [
				1,
				0
			],
			"loop": false,
			"fps": 24,
			"anim": "idle",
			"indices": [],
			"name": "idle"
		},
		{
			"offsets": [
				0,
				0
			],
			"loop": false,
			"fps": 24,
			"anim": "singDOWN",
			"indices": [],
			"name": "down0"
		},
		{
			"offsets": [
				0,
				0
			],
			"loop": false,
			"fps": 24,
			"anim": "singLEFT",
			"indices": [],
			"name": "left0"
		},
		{
			"offsets": [
				0,
				0
			],
			"loop": false,
			"fps": 24,
			"anim": "singRIGHT",
			"indices": [],
			"name": "right0"
		},
		{
			"offsets": [
				-10,
				236
			],
			"loop": false,
			"fps": 24,
			"anim": "singUP",
			"indices": [],
			"name": "up0"
		},
		{
			"offsets": [
				7,
				19
			],
			"loop": false,
			"fps": 24,
			"anim": "singLEFTmiss",
			"indices": [],
			"name": "left missed"
		},
		{
			"offsets": [
				-15,
				-19
			],
			"loop": false,
			"fps": 24,
			"anim": "singDOWNmiss",
			"indices": [],
			"name": "down missed"
		},
		{
			"offsets": [
				-46,
				227
			],
			"loop": false,
			"fps": 24,
			"anim": "singUPmiss",
			"indices": [],
			"name": "up missed"
		},
		{
			"offsets": [
				-44,
				22
			],
			"loop": false,
			"fps": 24,
			"anim": "singRIGHTmiss",
			"indices": [],
			"name": "right missed"
		}
	],
	"vocals_file": "",
	"no_antialiasing": false,
	"image": "characters/Room phase 1/mano_bf",
	"position": [
		200,
		550
	],
	"healthicon": "bf",
	"flip_x": true,
	"healthbar_colors": [
		49,
		176,
		209
	],
	"camera_position": [
		400,
		-300
	],
	"sing_duration": 4,
	"scale": 1,
	"_editor_isPlayer": true
}