{
	"animations": [
		{
			"offsets": [
				0,
				0
			],
			"loop": false,
			"fps": 24,
			"anim": "idle",
			"indices": [],
			"name": "Idle"
		},
		{
			"offsets": [
				312,
				-17
			],
			"loop": false,
			"fps": 24,
			"anim": "singLEFT",
			"indices": [],
			"name": "Left"
		},
		{
			"offsets": [
				8,
				6
			],
			"loop": false,
			"fps": 24,
			"anim": "singDOWN",
			"indices": [],
			"name": "Down"
		},
		{
			"offsets": [
				3,
				83
			],
			"loop": false,
			"fps": 24,
			"anim": "singUP",
			"indices": [],
			"name": "Up"
		},
		{
			"offsets": [
				-2,
				-8
			],
			"loop": false,
			"fps": 24,
			"anim": "singRIGHT",
			"indices": [],
			"name": "Right"
		}
	],
	"vocals_file": "",
	"no_antialiasing": false,
	"image": "characters/smiledogAlt1",
	"position": [
		250,
		-350
	],
	"healthicon": "dad",
	"flip_x": false,
	"healthbar_colors": [
		175,
		102,
		206
	],
	"camera_position": [
		-290,
		170
	],
	"sing_duration": 7.09999999999999,
	"scale": 2,
	"_editor_isPlayer": false
}